{
  "generatedAt": "2026-02-14T00:45:47.036Z",
  "totalSectors": 43,
  "threshold": 17,
  "sectors": [
    {
      "number": 1,
      "neighbors": [
        3
      ]
    },
    {
      "number": 2,
      "neighbors": [
        10,
        11,
        17,
        19
      ]
    },
    {
      "number": 3,
      "neighbors": [
        1,
        4,
        7
      ]
    },
    {
      "number": 4,
      "neighbors": [
        3,
        5,
        15,
        22
      ]
    },
    {
      "number": 5,
      "neighbors": [
        4,
        15
      ]
    },
    {
      "number": 7,
      "neighbors": [
        3,
        9
      ]
    },
    {
      "number": 9,
      "neighbors": [
        7,
        14,
        18
      ]
    },
    {
      "number": 10,
      "neighbors": [
        2,
        11
      ]
    },
    {
      "number": 11,
      "neighbors": [
        2,
        10,
        17
      ]
    },
    {
      "number": 14,
      "neighbors": [
        9,
        16,
        18
      ]
    },
    {
      "number": 15,
      "neighbors": [
        4,
        5,
        22
      ]
    },
    {
      "number": 16,
      "neighbors": [
        14,
        21
      ]
    },
    {
      "number": 17,
      "neighbors": [
        2,
        11,
        19,
        28
      ]
    },
    {
      "number": 18,
      "neighbors": [
        9,
        14
      ]
    },
    {
      "number": 19,
      "neighbors": [
        2,
        17,
        24
      ]
    },
    {
      "number": 21,
      "neighbors": [
        16,
        27
      ]
    },
    {
      "number": 22,
      "neighbors": [
        4,
        15
      ]
    },
    {
      "number": 24,
      "neighbors": [
        19
      ]
    },
    {
      "number": 25,
      "neighbors": [
        26,
        34,
        39
      ]
    },
    {
      "number": 26,
      "neighbors": [
        25,
        34
      ]
    },
    {
      "number": 27,
      "neighbors": [
        21
      ]
    },
    {
      "number": 28,
      "neighbors": [
        17,
        38
      ]
    },
    {
      "number": 34,
      "neighbors": [
        25,
        26,
        39
      ]
    },
    {
      "number": 35,
      "neighbors": [
        40,
        42
      ]
    },
    {
      "number": 36,
      "neighbors": [
        44
      ]
    },
    {
      "number": 38,
      "neighbors": [
        28,
        43
      ]
    },
    {
      "number": 39,
      "neighbors": [
        25,
        34
      ]
    },
    {
      "number": 40,
      "neighbors": [
        35,
        42,
        45,
        46
      ]
    },
    {
      "number": 41,
      "neighbors": [
        47,
        51
      ]
    },
    {
      "number": 42,
      "neighbors": [
        35,
        40,
        46,
        53,
        55
      ]
    },
    {
      "number": 43,
      "neighbors": [
        38,
        47,
        51,
        54
      ]
    },
    {
      "number": 44,
      "neighbors": [
        36,
        48,
        59
      ]
    },
    {
      "number": 45,
      "neighbors": [
        40,
        46,
        50
      ]
    },
    {
      "number": 46,
      "neighbors": [
        40,
        42,
        45,
        50,
        53
      ]
    },
    {
      "number": 47,
      "neighbors": [
        41,
        43,
        51
      ]
    },
    {
      "number": 48,
      "neighbors": [
        44,
        56,
        59
      ]
    },
    {
      "number": 50,
      "neighbors": [
        45,
        46,
        53
      ]
    },
    {
      "number": 51,
      "neighbors": [
        41,
        43,
        47,
        54
      ]
    },
    {
      "number": 53,
      "neighbors": [
        42,
        46,
        50
      ]
    },
    {
      "number": 54,
      "neighbors": [
        43,
        51
      ]
    },
    {
      "number": 55,
      "neighbors": [
        42,
        56
      ]
    },
    {
      "number": 56,
      "neighbors": [
        48,
        55,
        59
      ]
    },
    {
      "number": 59,
      "neighbors": [
        44,
        48,
        56
      ]
    }
  ]
}